mlx_genkit/__init__.py
mlx_genkit/adapters.py
mlx_genkit/api.py
mlx_genkit/cli.py
mlx_genkit/config.py
mlx_genkit/diagnostics.py
mlx_genkit/eval.py
mlx_genkit/injection.py
mlx_genkit/interop.py
mlx_genkit/loader.py
mlx_genkit/sampling.py
mlx_genkit/training.py
mlx_genkit/utils.py
mlx_genkit/backends/__init__.py
mlx_genkit/backends/base.py
mlx_genkit/backends/mlx_backend.py
mlx_genkit/backends/transformers_backend.py
mlx_genkit/backends/vllm_backend.py
mlx_genkit/data/loader.py
mlx_genkit/rl/ppo.py
mlx_genkit/rl/utils.py
mlx_genkit/structure/adherence.py
mlx_genkit/structure/batch.py
mlx_genkit/structure/dsl.py
mlx_genkit/structure/grammar.py
mlx_genkit/structure/logs.py
mlx_genkit/structure/result.py
mlx_genkit/structure/semantic.py
mlx_genkit/structure/stream.py
mlx_genkit/structure/validators.py
mlx_genkit/tests/harness.py
mlx_genkit/tests/parity_hf.py
mlx_genkit/tests/parity_suite.py
mlx_genkit/tests/perf_bench.py
mlx_genkit/tests/test_eval_unit.py
mlx_genkit/tests/test_structure_unit.py
mlx_genkit/tests/utils_demo.py
mlx_genkit-0.4.4.dist-info/METADATA
mlx_genkit-0.4.4.dist-info/WHEEL
mlx_genkit-0.4.4.dist-info/entry_points.txt
mlx_genkit-0.4.4.dist-info/top_level.txt
mlx_genkit-0.4.4.dist-info/RECORD
