Metadata-Version: 2.4
Name: mlx-genkit
Version: 0.4.4
Summary: MLX generation parity utils with HF/Torch-compatible sampling, processors, and steering hooks
Author: Your Team
Project-URL: Homepage, https://github.com/strangeloopcanon/mlx-genkit
Classifier: License :: OSI Approved :: Apache Software License
Classifier: Programming Language :: Python :: 3
Requires-Python: >=3.9
Requires-Dist: mlx>=0.17.0
Requires-Dist: mlx-lm>=0.17.0
Requires-Dist: transformers>=4.40.0; python_version >= "3.9"
